ideal_rcf/__init__.py
ideal_rcf/dataloader/__init__.py
ideal_rcf/dataloader/caseset.py
ideal_rcf/dataloader/config.py
ideal_rcf/dataloader/dataset.py
ideal_rcf/foam/__init__.py
ideal_rcf/foam/postprocess.py
ideal_rcf/foam/preprocess.py
ideal_rcf/foam/visualization.py
ideal_rcf/infrastructure/__init__.py
ideal_rcf/infrastructure/cross_validation.py
ideal_rcf/infrastructure/evaluator.py
ideal_rcf/infrastructure/visualization.py
ideal_rcf/models/__init__.py
ideal_rcf/models/base_model.py
ideal_rcf/models/config.py
ideal_rcf/models/evnn.py
ideal_rcf/models/framework.py
ideal_rcf/models/mixer.py
ideal_rcf/models/oevnn.py
ideal_rcf/models/sstbnnz.py
ideal_rcf/models/tbnn.py
ideal_rcf/models/utils.py
ideal_rcf-0.3a3.dist-info/LICENSE
ideal_rcf-0.3a3.dist-info/METADATA
ideal_rcf-0.3a3.dist-info/WHEEL
ideal_rcf-0.3a3.dist-info/top_level.txt
ideal_rcf-0.3a3.dist-info/RECORD
