Metadata-Version: 2.1
Name: ideal_rcf
Version: 0.3a3
Summary: A python framework for invariant rans turbulence closure.
Home-page: https://github.com/BrunoV21/IDeaL_RCF
Author: bruno_v
Author-email: bruno.vitorino@tecnico.ulisboa.pt
Classifier: Programming Language :: Python :: 3.9
Classifier: License :: OSI Approved :: MIT License
Classifier: Operating System :: OS Independent
License-File: LICENSE
Requires-Dist: gdown ==5.2.0
Requires-Dist: matplotlib ==3.7.1
Requires-Dist: polars ==1.0.0
Requires-Dist: scikit-learn ==1.2.2
Requires-Dist: tqdm ==4.41.1
Requires-Dist: typing-extensions ==4.8.0
Requires-Dist: numpy ==1.25.2
Requires-Dist: tensorflow ==2.15.0
